setup.cfg
setup.py
optimizely_platform/__init__.py
optimizely_platform/exceptions.py
optimizely_platform/objects.py
optimizely_platform/utils.py
optimizely_platform.egg-info/PKG-INFO
optimizely_platform.egg-info/SOURCES.txt
optimizely_platform.egg-info/dependency_links.txt
optimizely_platform.egg-info/top_level.txt