Metadata-Version: 1.1
Name: optimizely-platform
Version: 0.0.7
Summary: Package providing modules needed to build add-ons that run natively in the Optimizely platform.
Home-page: https://github.com/optimizely/optimizely-platform
Author: Jon Gaulding, Tyler Jones, Peng-Wen Chen, Ali Rizvi
Author-email: developers@optimizely.com
License: MIT
Download-URL: https://github.com/optimizely/optimizely-platform/tarball/0.0.7
Keywords: optimizely,platform,integration,add-on
Platform: UNKNOWN
Classifier: Development Status :: 4 - Beta
Classifier: Environment :: Web Environment
Classifier: Intended Audience :: Developers
Classifier: Operating System :: OS Independent
Classifier: Programming Language :: Python
Classifier: Programming Language :: Python :: 2.7
Classifier: Programming Language :: Python :: 3.4
